granted_flask/__init__.py
granted_flask/shell.py
granted_flask-0.1.13.dist-info/entry_points.txt
granted_flask-0.1.13.dist-info/WHEEL
granted_flask-0.1.13.dist-info/METADATA
granted_flask-0.1.13.dist-info/RECORD
