Metadata-Version: 2.1
Name: granted-flask
Version: 0.1.13
Summary: 
Author: Common Fate
Author-email: hello@commonfate.io
Requires-Python: >=3.10,<4.0
Classifier: Programming Language :: Python :: 3
Classifier: Programming Language :: Python :: 3.10
Requires-Dist: python-dotenv (>=0.20.0,<0.21.0)
Requires-Dist: requests (>=2.28.1,<3.0.0)
